discorebots/__database__.py
discorebots/__defines__.py
discorebots/__init__.py
discorebots/__versions__.py
discorebots/classes.py
discorebots/defines.py
discorebots/discorebots.py
discorebots-0.0.75.dist-info/METADATA
discorebots-0.0.75.dist-info/WHEEL
discorebots-0.0.75.dist-info/top_level.txt
discorebots-0.0.75.dist-info/RECORD
