Metadata-Version: 2.1
Name: discorebots
Version: 0.0.75
Summary: Package to create discord bots its easy!
Home-page: UNKNOWN
Author: SScefaLI
Author-email: birka11@list.ru
License: UNKNOWN
Platform: UNKNOWN
Classifier: Programming Language :: Python :: 3
Classifier: License :: OSI Approved :: MIT License
Classifier: Operating System :: OS Independent
Requires-Python: >=3.8
Requires-Dist: disnake
Requires-Dist: requests
Requires-Dist: asyncio
Requires-Dist: colorama
Requires-Dist: betterjsondb
